examples/__init__.py
examples/annotate_wikipedia.py
examples/download_glue_data.py
examples/entity_linking.py
examples/ner.py
relogic/__init__.py
relogic/_version.py
relogic/main.py
relogic/main_tpu.py
relogic/common/__init__.py
relogic/common/checks.py
relogic/common/prefix_map.py
relogic/components/__init__.py
relogic/components/component.py
relogic/components/entity_linking_component.py
relogic/components/ner_component.py
relogic/components/predicate_detection_component.py
relogic/components/srl_component.py
relogic/graphkit/__init__.py
relogic/graphkit/linking/__init__.py
relogic/graphkit/linking/simple_entity_linker.py
relogic/graphkit/utils/__init__.py
relogic/graphkit/utils/similarity_function.py
relogic/logickit/__init__.py
relogic/logickit/analyzer/__init__.py
relogic/logickit/analyzer/heads_importance.py
relogic/logickit/base/__init__.py
relogic/logickit/base/config.py
relogic/logickit/base/configuration.py
relogic/logickit/base/configuration_trainer.py
relogic/logickit/base/configuration_utils.py
relogic/logickit/base/configuration_xlm.py
relogic/logickit/base/configure.py
relogic/logickit/base/constants.py
relogic/logickit/base/utils.py
relogic/logickit/dataflow/__init__.py
relogic/logickit/dataflow/dataflow.py
relogic/logickit/dataflow/dep.py
relogic/logickit/dataflow/doc_pointwise.py
relogic/logickit/dataflow/ecp.py
relogic/logickit/dataflow/mixsent.py
relogic/logickit/dataflow/pairwise.py
relogic/logickit/dataflow/parallel.py
relogic/logickit/dataflow/pointwise.py
relogic/logickit/dataflow/sequence.py
relogic/logickit/dataflow/singleton.py
relogic/logickit/dataflow/srl.py
relogic/logickit/dataflow/twins.py
relogic/logickit/dataset/__init__.py
relogic/logickit/dataset/labeled_data_loader.py
relogic/logickit/dataset/lazy_dataset.py
relogic/logickit/inference/__init__.py
relogic/logickit/inference/adversarial.py
relogic/logickit/inference/branching_encoder.py
relogic/logickit/inference/encoder.py
relogic/logickit/inference/inference.py
relogic00-0.0.1.dist-info/METADATA
relogic00-0.0.1.dist-info/WHEEL
relogic00-0.0.1.dist-info/top_level.txt
relogic00-0.0.1.dist-info/RECORD
